pactum/__init__.py
pactum/__version__.py
pactum/api.py
pactum/base.py
pactum/exceptions.py
pactum/route.py
pactum/version.py
pactum-0.0.1.dist-info/DESCRIPTION.rst
pactum-0.0.1.dist-info/METADATA
pactum-0.0.1.dist-info/RECORD
pactum-0.0.1.dist-info/WHEEL
pactum-0.0.1.dist-info/metadata.json
pactum-0.0.1.dist-info/top_level.txt
